whatthepatch_pydantic/__init__.py
whatthepatch_pydantic/apply.py
whatthepatch_pydantic/exceptions.py
whatthepatch_pydantic/model.py
whatthepatch_pydantic/patch.py
whatthepatch_pydantic/snippets.py
whatthepatch_pydantic-1.0.6a3.dist-info/LICENSE
whatthepatch_pydantic-1.0.6a3.dist-info/METADATA
whatthepatch_pydantic-1.0.6a3.dist-info/WHEEL
whatthepatch_pydantic-1.0.6a3.dist-info/top_level.txt
whatthepatch_pydantic-1.0.6a3.dist-info/RECORD
