Metadata-Version: 2.1
Name: whatthepatch-pydantic
Version: 1.0.6a3
Summary: A patch parsing and application library.
Maintainer-email: "Christopher S. Corley" <cscorley@gmail.com>, jingfelix <jingfelix@outlook.com>
Project-URL: Homepage, https://github.com/jingfelix/whatthepatch
Project-URL: Bug Tracker, https://github.com/jingfelix/whatthepatch/issues
Keywords: patch,diff,parser
Classifier: Development Status :: 5 - Production/Stable
Classifier: Intended Audience :: Developers
Classifier: Intended Audience :: Science/Research
Classifier: License :: OSI Approved :: MIT License
Classifier: Operating System :: OS Independent
Classifier: Programming Language :: Python :: 3 :: Only
Classifier: Programming Language :: Python :: 3
Classifier: Programming Language :: Python :: 3.7
Classifier: Programming Language :: Python :: 3.8
Classifier: Programming Language :: Python :: 3.9
Classifier: Programming Language :: Python :: 3.10
Classifier: Programming Language :: Python :: 3.11
Classifier: Programming Language :: Python :: Implementation :: CPython
Classifier: Topic :: Software Development :: Libraries :: Python Modules
Classifier: Topic :: Software Development :: Version Control
Classifier: Topic :: Software Development
Classifier: Topic :: Text Processing
Requires-Python: >=3.7
License-File: LICENSE
